zerohero/__init__.py
zerohero/embedding_functions/openai_.py
zerohero/embedding_functions/sentence_transformers_.py
zerohero-0.1.4.dist-info/METADATA
zerohero-0.1.4.dist-info/WHEEL
zerohero-0.1.4.dist-info/RECORD
