Metadata-Version: 2.1
Name: zerohero
Version: 0.1.4
Summary: Easy Embedding-Based Zero-Shot Classfication
License: MIT
Author: edkrueger
Author-email: edkrueger@gmail.com
Requires-Python: >=3.10,<3.13
Classifier: License :: OSI Approved :: MIT License
Classifier: Programming Language :: Python :: 3
Classifier: Programming Language :: Python :: 3.10
Classifier: Programming Language :: Python :: 3.11
Classifier: Programming Language :: Python :: 3.12
Requires-Dist: backoff (>=2.2.1,<3.0.0)
Requires-Dist: openai (>=0.28.1,<0.29.0)
Requires-Dist: sentence-transformers (>=2.2.2,<3.0.0)
Requires-Dist: tiktoken (>=0.5.1,<0.6.0)
Requires-Dist: torch (>=2.1.0,<3.0.0)
